{
  "profileId": "XADES_JUSTACT_CITIZEN_FR",
  "digestAlgorithm": "SHA384",
  "referenceDigestAlgorithm": "SHA512",
  "signatureLevel": "XAdES_BASELINE_LTA",
  "signaturePackaging": "DETACHED",
  "signatureForm": "XAdES",
  "tspServer": "http://tss.eidpki.belgium.be/",
  "trustAnchorBPPolicy": false,
  "revocationStrategy": "OCSP_ONLY_FOR_LEAF",
  "policyId": "https://epolicies.just.fgov.be/justact/esign-policy/eSignature_policy_justact_fr_v1.1.pdf",
  "policyDescription": "Service Public F\u00e9d\u00e9ral Belge Justice",
  "policyDigestAlgorithm": "SHA512",
  "policyDigestValue": "0eH6/qwppOLwfLx8B4IJ1IGx/VPce7tkUEdDySTKGF5dml0HoALfPWs2TD16oOJr0V3qSn9mVVv5sTxIQDKdUw==",
  "signingType": "MultiFileDetached"
}
